{
  "junctions": [
    [
      [
        "0"
      ],
      [
        "1",
        "2"
      ]
    ]
  ],
  "links": [
    {
      "fd": {
        "q_max": 10.0,
        "rho_max": 10.0,
        "w": 1.0,
        "v": 1.0
      },
      "name": "2",
      "rho": 1,
      "l": 1
    },
    {
      "fd": {
        "q_max": 10.0,
        "rho_max": 10.0,
        "w": 1.0,
        "v": 1.0
      },
      "name": "0",
      "rho": 1,
      "l": 1
    },
    {
      "fd": {
        "q_max": 10.0,
        "rho_max": 10.0,
        "w": 1.0,
        "v": 1.0
      },
      "name": "1",
      "rho": 1,
      "l": 1
    }
  ]
}